compile_time_printer/__init__.py
compile_time_printer/ctp.py
compile_time_printer/include/ctp/ctp.hpp
compile_time_printer-1.2.0.dist-info/LICENSE.txt
compile_time_printer-1.2.0.dist-info/METADATA
compile_time_printer-1.2.0.dist-info/WHEEL
compile_time_printer-1.2.0.dist-info/entry_points.txt
compile_time_printer-1.2.0.dist-info/top_level.txt
compile_time_printer-1.2.0.dist-info/RECORD
