Metadata-Version: 2.1
Name: compile-time-printer
Version: 1.2.0
Summary: A tool for printing values and types at compile-time in C++.
Home-page: https://github.com/pyscaffold/pyscaffold/
Author: Toni Neubert
Author-email: lutztonineubert@gmail.com
License: BSL-1.0
Project-URL: Documentation, https://github.com/Viatorus/compile-time-printer
Project-URL: Source, https://github.com/Viatorus/compile-time-printer
Platform: any
Classifier: Development Status :: 4 - Beta
Classifier: Programming Language :: Python :: 3
Classifier: License :: OSI Approved :: Boost Software License 1.0 (BSL-1.0)
Requires-Python: >=3.6
License-File: LICENSE.txt
Requires-Dist: importlib-metadata; python_version < "3.8"
Provides-Extra: testing
Requires-Dist: pytest; extra == "testing"
Requires-Dist: pytest-cov; extra == "testing"
Requires-Dist: flake8; extra == "testing"
Requires-Dist: flake8-quotes; extra == "testing"
